mkgmap_github_action.py
mkgmap_github_action-0.20.0.dist-info/METADATA
mkgmap_github_action-0.20.0.dist-info/WHEEL
mkgmap_github_action-0.20.0.dist-info/entry_points.txt
mkgmap_github_action-0.20.0.dist-info/RECORD
