Metadata-Version: 2.4
Name: mkgmap-github-action
Version: 0.20.0
Summary: 
Author: Dick Marinus
Author-email: dick@mrns.nl
Requires-Python: >=3.9,<3.15
Classifier: Programming Language :: Python :: 3
Classifier: Programming Language :: Python :: 3.9
Classifier: Programming Language :: Python :: 3.10
Classifier: Programming Language :: Python :: 3.11
Classifier: Programming Language :: Python :: 3.12
Classifier: Programming Language :: Python :: 3.13
Classifier: Programming Language :: Python :: 3.14
Requires-Dist: Jinja2 (>=3.1.2,<4.0.0)
Requires-Dist: requests (>=2.28.1,<3.0.0)
